yandex_query_client/__init__.py
yandex_query_client/http_client.py
yandex_query_client/query_results.py
yandex_query_client-0.1.3.dist-info/METADATA
yandex_query_client-0.1.3.dist-info/WHEEL
yandex_query_client-0.1.3.dist-info/licenses/LICENSE.md
yandex_query_client-0.1.3.dist-info/RECORD
